bloodaxe.py
bloodaxe-0.2.0.dist-info/entry_points.txt
bloodaxe-0.2.0.dist-info/LICENSE
bloodaxe-0.2.0.dist-info/WHEEL
bloodaxe-0.2.0.dist-info/METADATA
bloodaxe-0.2.0.dist-info/RECORD
